send_2_llm/__init__.py
send_2_llm/api.py
send_2_llm/cli.py
send_2_llm/client.py
send_2_llm/config.py
send_2_llm/formatters.py
send_2_llm/manager.py
send_2_llm/response_formatter.py
send_2_llm/types.py
send_2_llm/cli/__init__.py
send_2_llm/cli/console.py
send_2_llm/cli/commands/__init__.py
send_2_llm/cli/commands/base.py
send_2_llm/cli/commands/config.py
send_2_llm/cli/commands/interactive.py
send_2_llm/cli/commands/logs.py
send_2_llm/cli/commands/single_shot.py
send_2_llm/cli/utils/__init__.py
send_2_llm/cli/utils/config.py
send_2_llm/cli/utils/formatting.py
send_2_llm/cli/utils/log_analysis.py
send_2_llm/cli/utils/log_rotation.py
send_2_llm/cli/utils/logging.py
send_2_llm/cli/utils/validation.py
send_2_llm/constants/__init__.py
send_2_llm/constants/config_loader.py
send_2_llm/constants/config_manager.py
send_2_llm/constants/defaults.yaml
send_2_llm/constants/model_configs.yaml
send_2_llm/constants/model_pricing.py
send_2_llm/constants/model_pricing.yaml
send_2_llm/constants/provider_features.yaml
send_2_llm/constants/system_prompts.yaml
send_2_llm/logging/__init__.py
send_2_llm/logging/api.py
send_2_llm/logging/metrics.py
send_2_llm/monitoring/__init__.py
send_2_llm/monitoring/metrics.py
send_2_llm/providers/__init__.py
send_2_llm/providers/anthropic_provider.py
send_2_llm/providers/base.py
send_2_llm/providers/deepseek_provider.py
send_2_llm/providers/factory.py
send_2_llm/providers/gemini_provider.py
send_2_llm/providers/manager.py
send_2_llm/providers/openai.py
send_2_llm/providers/openai_provider.py
send_2_llm/providers/perplexity_provider.py
send_2_llm/providers/together_provider.py
send_2_llm/security/manager.py
send_2_llm/stability/__init__.py
send_2_llm/stability/circuit_breaker.py
send_2_llm/stability/rate_limiter.py
send_2_llm/strategies/__init__.py
send_2_llm/strategies/base.py
send_2_llm/strategies/fallback.py
send_2_llm/strategies/single.py
send_2_llm/strategies/together_strategy.py
send_2_llm/strategy/base.py
send_2_llm/strategy/fallback.py
send_2_llm-0.9.7.dist-info/LICENSE
send_2_llm-0.9.7.dist-info/METADATA
send_2_llm-0.9.7.dist-info/WHEEL
send_2_llm-0.9.7.dist-info/top_level.txt
send_2_llm-0.9.7.dist-info/RECORD
